{"nodes": [{"id": "codeblock_fencesyntax", "label": "Code Block Fence Syntax", "file_type": "document", "source_file": "docs/05-code-blocks.md", "source_location": null, "source_url": null, "captured_at": null, "author": null, "contributor": null}, {"id": "codeblock_syntaxpipeline", "label": "Syntax Coloring Pipeline (5 Steps)", "file_type": "document", "source_file": "docs/05-code-blocks.md", "source_location": null, "source_url": null, "captured_at": null, "author": null, "contributor": null}, {"id": "codeblock_minfold", "label": "Code Block :min Folding Mechanism", "file_type": "document", "source_file": "docs/05-code-blocks.md", "source_location": null, "source_url": null, "captured_at": null, "author": null, "contributor": null}, {"id": "codeblock_ln", "label": "Code Block :ln Line Numbers", "file_type": "document", "source_file": "docs/05-code-blocks.md", "source_location": null, "source_url": null, "captured_at": null, "author": null, "contributor": null}, {"id": "codeblock_overlaybuttons", "label": "Code Block Overlay Buttons (#/\u25be/Copy/Delete)", "file_type": "document", "source_file": "docs/05-code-blocks.md", "source_location": null, "source_url": null, "captured_at": null, "author": null, "contributor": null}, {"id": "codeblock_codeblockformat", "label": "Code Block Clipboard Format (application/x-mynotepad-codeblock)", "file_type": "document", "source_file": "docs/05-code-blocks.md", "source_location": null, "source_url": null, "captured_at": null, "author": null, "contributor": null}], "edges": [{"source": "codeblock_fencesyntax", "target": "overview_codeblockparser", "relation": "references", "confidence": "EXTRACTED", "confidence_score": 1.0, "source_file": "docs/05-code-blocks.md", "source_location": null, "weight": 1.0}, {"source": "codeblock_syntaxpipeline", "target": "overview_codesyntaxcolorizer", "relation": "references", "confidence": "EXTRACTED", "confidence_score": 1.0, "source_file": "docs/05-code-blocks.md", "source_location": null, "weight": 1.0}, {"source": "codeblock_minfold", "target": "arch_foldingmanager", "relation": "references", "confidence": "EXTRACTED", "confidence_score": 1.0, "source_file": "docs/05-code-blocks.md", "source_location": null, "weight": 1.0}, {"source": "codeblock_minfold", "target": "overview_codeblockcollapsegenerator", "relation": "references", "confidence": "EXTRACTED", "confidence_score": 1.0, "source_file": "docs/05-code-blocks.md", "source_location": null, "weight": 1.0}, {"source": "codeblock_minfold", "target": "arch_reparseblocks", "relation": "references", "confidence": "EXTRACTED", "confidence_score": 1.0, "source_file": "docs/05-code-blocks.md", "source_location": null, "weight": 1.0}, {"source": "codeblock_ln", "target": "overview_codeblocklngenerator", "relation": "references", "confidence": "EXTRACTED", "confidence_score": 1.0, "source_file": "docs/05-code-blocks.md", "source_location": null, "weight": 1.0}, {"source": "codeblock_ln", "target": "overview_codeblocklnrenderer", "relation": "references", "confidence": "EXTRACTED", "confidence_score": 1.0, "source_file": "docs/05-code-blocks.md", "source_location": null, "weight": 1.0}, {"source": "codeblock_overlaybuttons", "target": "overview_codeblockcopyoverlay", "relation": "references", "confidence": "EXTRACTED", "confidence_score": 1.0, "source_file": "docs/05-code-blocks.md", "source_location": null, "weight": 1.0}, {"source": "codeblock_codeblockformat", "target": "overview_richclipboard", "relation": "references", "confidence": "EXTRACTED", "confidence_score": 1.0, "source_file": "docs/05-code-blocks.md", "source_location": null, "weight": 1.0}], "hyperedges": [{"id": "codeblock_rendering_components", "label": "Code Block Rendering Components", "nodes": ["overview_codeblockbackgroundrenderer", "overview_codeblockcollapsegenerator", "overview_codesyntaxcolorizer", "overview_codeblockpaddingtransformer", "overview_codeblocklngenerator", "overview_codeblockfonttransformer"], "relation": "implement", "confidence": "EXTRACTED", "confidence_score": 1.0, "source_file": "docs/05-code-blocks.md"}]}