{"nodes": [{"id": "c_developer_repos_utils_mynotepad_config_appsettings_cs", "label": "AppSettings.cs", "file_type": "code", "source_file": "C:\\Developer\\repos-utils\\MyNotepad\\Config\\AppSettings.cs", "source_location": "L1"}, {"id": "appsettings_minimalnotepad_config", "label": "MinimalNotepad.Config", "file_type": "code", "source_file": "C:\\Developer\\repos-utils\\MyNotepad\\Config\\AppSettings.cs", "source_location": "L1"}, {"id": "appsettings_appsettings", "label": "AppSettings", "file_type": "code", "source_file": "C:\\Developer\\repos-utils\\MyNotepad\\Config\\AppSettings.cs", "source_location": "L3"}], "edges": [{"source": "c_developer_repos_utils_mynotepad_config_appsettings_cs", "target": "appsettings_minimalnotepad_config", "relation": "contains", "confidence": "EXTRACTED", "source_file": "C:\\Developer\\repos-utils\\MyNotepad\\Config\\AppSettings.cs", "source_location": "L1", "weight": 1.0}, {"source": "c_developer_repos_utils_mynotepad_config_appsettings_cs", "target": "appsettings_appsettings", "relation": "contains", "confidence": "EXTRACTED", "source_file": "C:\\Developer\\repos-utils\\MyNotepad\\Config\\AppSettings.cs", "source_location": "L3", "weight": 1.0}], "raw_calls": []}